sporosdk/__init__.py
sporosdk/client.py
sporosdk-0.1.0.dist-info/METADATA
sporosdk-0.1.0.dist-info/WHEEL
sporosdk-0.1.0.dist-info/top_level.txt
sporosdk-0.1.0.dist-info/RECORD
