Metadata-Version: 2.1
Name: sporosdk
Version: 0.1.0
Summary: A Python SDK for interacting with the Sporo API to generate summaries.
Home-page: https://github.com/yourusername/sporosdk
Author: Team Sporo Health
Author-email: contact@sporohealth.com
Classifier: Programming Language :: Python :: 3
Classifier: License :: OSI Approved :: MIT License
Classifier: Operating System :: OS Independent
Requires-Python: >=3.8
Requires-Dist: requests
